{
    "frames": [
        {
            "filename": "1_0",
            "frame": {
                "w": 100,
                "h": 100,
                "x": 1,
                "y": 1
            },
            "anchor": {
                "x": 0.5,
                "y": 0.5
            }
        },
        {
            "filename": "1_1",
            "frame": {
                "w": 100,
                "h": 100,
                "x": 102,
                "y": 1
            },
            "anchor": {
                "x": 0.5,
                "y": 0.5
            }
        },
        {
            "filename": "1_2",
            "frame": {
                "w": 100,
                "h": 100,
                "x": 1,
                "y": 102
            },
            "anchor": {
                "x": 0.5,
                "y": 0.5
            }
        },
        {
            "filename": "1_3",
            "frame": {
                "w": 100,
                "h": 100,
                "x": 102,
                "y": 102
            },
            "anchor": {
                "x": 0.5,
                "y": 0.5
            }
        },
        {
            "filename": "1_4",
            "frame": {
                "w": 100,
                "h": 100,
                "x": 203,
                "y": 1
            },
            "anchor": {
                "x": 0.5,
                "y": 0.5
            }
        },
        {
            "filename": "1_5",
            "frame": {
                "w": 100,
                "h": 100,
                "x": 203,
                "y": 102
            },
            "anchor": {
                "x": 0.5,
                "y": 0.5
            }
        },
        {
            "filename": "1_6",
            "frame": {
                "w": 100,
                "h": 100,
                "x": 1,
                "y": 203
            },
            "anchor": {
                "x": 0.5,
                "y": 0.5
            }
        },
        {
            "filename": "1_7",
            "frame": {
                "w": 100,
                "h": 100,
                "x": 102,
                "y": 203
            },
            "anchor": {
                "x": 0.5,
                "y": 0.5
            }
        },
        {
            "filename": "1_8",
            "frame": {
                "w": 100,
                "h": 100,
                "x": 203,
                "y": 203
            },
            "anchor": {
                "x": 0.5,
                "y": 0.5
            }
        },
        {
            "filename": "1_9",
            "frame": {
                "w": 100,
                "h": 100,
                "x": 304,
                "y": 1
            },
            "anchor": {
                "x": 0.5,
                "y": 0.5
            }
        },
        {
            "filename": "1_10",
            "frame": {
                "w": 100,
                "h": 100,
                "x": 304,
                "y": 102
            },
            "anchor": {
                "x": 0.5,
                "y": 0.5
            }
        },
        {
            "filename": "1_11",
            "frame": {
                "w": 100,
                "h": 100,
                "x": 304,
                "y": 203
            },
            "anchor": {
                "x": 0.5,
                "y": 0.5
            }
        },
        {
            "filename": "1_12",
            "frame": {
                "w": 100,
                "h": 100,
                "x": 1,
                "y": 304
            },
            "anchor": {
                "x": 0.5,
                "y": 0.5
            }
        },
        {
            "filename": "1_13",
            "frame": {
                "w": 100,
                "h": 100,
                "x": 102,
                "y": 304
            },
            "anchor": {
                "x": 0.5,
                "y": 0.5
            }
        },
        {
            "filename": "1_14",
            "frame": {
                "w": 100,
                "h": 100,
                "x": 203,
                "y": 304
            },
            "anchor": {
                "x": 0.5,
                "y": 0.5
            }
        },
        {
            "filename": "1_15",
            "frame": {
                "w": 100,
                "h": 100,
                "x": 304,
                "y": 304
            },
            "anchor": {
                "x": 0.5,
                "y": 0.5
            }
        },
        {
            "filename": "1_16",
            "frame": {
                "w": 100,
                "h": 100,
                "x": 405,
                "y": 1
            },
            "anchor": {
                "x": 0.5,
                "y": 0.5
            }
        },
        {
            "filename": "1_17",
            "frame": {
                "w": 100,
                "h": 100,
                "x": 405,
                "y": 102
            },
            "anchor": {
                "x": 0.5,
                "y": 0.5
            }
        },
        {
            "filename": "1_18",
            "frame": {
                "w": 100,
                "h": 100,
                "x": 405,
                "y": 203
            },
            "anchor": {
                "x": 0.5,
                "y": 0.5
            }
        },
        {
            "filename": "1_19",
            "frame": {
                "w": 100,
                "h": 100,
                "x": 405,
                "y": 304
            },
            "anchor": {
                "x": 0.5,
                "y": 0.5
            }
        },
        {
            "filename": "1_20",
            "frame": {
                "w": 100,
                "h": 100,
                "x": 1,
                "y": 405
            },
            "anchor": {
                "x": 0.5,
                "y": 0.5
            }
        },
        {
            "filename": "1_21",
            "frame": {
                "w": 100,
                "h": 100,
                "x": 102,
                "y": 405
            },
            "anchor": {
                "x": 0.5,
                "y": 0.5
            }
        },
        {
            "filename": "1_22",
            "frame": {
                "w": 100,
                "h": 100,
                "x": 203,
                "y": 405
            },
            "anchor": {
                "x": 0.5,
                "y": 0.5
            }
        },
        {
            "filename": "1_23",
            "frame": {
                "w": 100,
                "h": 100,
                "x": 304,
                "y": 405
            },
            "anchor": {
                "x": 0.5,
                "y": 0.5
            }
        },
        {
            "filename": "1_24",
            "frame": {
                "w": 100,
                "h": 100,
                "x": 405,
                "y": 405
            },
            "anchor": {
                "x": 0.5,
                "y": 0.5
            }
        },
        {
            "filename": "1_25",
            "frame": {
                "w": 100,
                "h": 100,
                "x": 506,
                "y": 1
            },
            "anchor": {
                "x": 0.5,
                "y": 0.5
            }
        },
        {
            "filename": "1_26",
            "frame": {
                "w": 100,
                "h": 100,
                "x": 506,
                "y": 102
            },
            "anchor": {
                "x": 0.5,
                "y": 0.5
            }
        },
        {
            "filename": "1_27",
            "frame": {
                "w": 100,
                "h": 100,
                "x": 506,
                "y": 203
            },
            "anchor": {
                "x": 0.5,
                "y": 0.5
            }
        },
        {
            "filename": "1_28",
            "frame": {
                "w": 100,
                "h": 100,
                "x": 506,
                "y": 304
            },
            "anchor": {
                "x": 0.5,
                "y": 0.5
            }
        },
        {
            "filename": "1_29",
            "frame": {
                "w": 100,
                "h": 100,
                "x": 506,
                "y": 405
            },
            "anchor": {
                "x": 0.5,
                "y": 0.5
            }
        }
    ],
    "meta": {
        "description": "Atlas generado con Atlas Packer Gamma V2",
        "web": "https://gammafp.github.io/atlas-packer-phaser/"
    }
}